gitree/__init__.py
gitree/main.py
gitree/constants/__init__.py
gitree/constants/constant.py
gitree/objects/__init__.py
gitree/objects/app_context.py
gitree/objects/config.py
gitree/objects/gitignore.py
gitree/services/__init__.py
gitree/services/copy_service.py
gitree/services/drawing_service.py
gitree/services/export_service.py
gitree/services/general_options_service.py
gitree/services/interactive_selection_service.py
gitree/services/items_selection_service.py
gitree/services/parsing_service.py
gitree/services/zipping_service.py
gitree/utilities/__init__.py
gitree/utilities/color_utility.py
gitree/utilities/functions_utility.py
gitree/utilities/gitignore_utility.py
gitree/utilities/logging_utility.py
gitree-0.4.0.dist-info/licenses/LICENSE
gitree-0.4.0.dist-info/METADATA
gitree-0.4.0.dist-info/WHEEL
gitree-0.4.0.dist-info/entry_points.txt
gitree-0.4.0.dist-info/top_level.txt
gitree-0.4.0.dist-info/RECORD
