Metadata-Version: 2.4
Name: gitree
Version: 0.4.0
Summary: gitree: git-aware project tree printing and zipping for docs and LLMs
Author: Shahzaib Ahmad
License: MIT
Project-URL: Homepage, https://github.com/ShahzaibAhmad05/gitree
Project-URL: Repository, https://github.com/ShahzaibAhmad05/gitree
Project-URL: Issues, https://github.com/ShahzaibAhmad05/gitree/issues
Project-URL: Changelog, https://github.com/ShahzaibAhmad05/gitree/releases
Keywords: tree,directory-tree,git,gitignore,cli,docs,llm
Classifier: Development Status :: 4 - Beta
Classifier: Environment :: Console
Classifier: Intended Audience :: Developers
Classifier: License :: OSI Approved :: MIT License
Classifier: Operating System :: OS Independent
Classifier: Programming Language :: Python :: 3
Classifier: Programming Language :: Python :: 3 :: Only
Classifier: Programming Language :: Python :: 3.11
Classifier: Programming Language :: Python :: 3.12
Classifier: Programming Language :: Python :: 3.13
Classifier: Programming Language :: Python :: 3.14
Classifier: Topic :: Software Development :: Documentation
Classifier: Topic :: Utilities
Requires-Python: >=3.11
License-File: LICENSE
Requires-Dist: pathspec>=0.11
Requires-Dist: pyperclip>=1.5
Requires-Dist: prompt_toolkit>=3.0
Dynamic: license-file
